[
  {
    "province": "宁夏",
    "year": 2023,
    "track": "历史类",
    "schoolName": "宁夏大学",
    "schoolId": 544,
    "minScore": 579,
    "minRank": 8811,
    "avgScore": "-",
    "batch": "本科批",
    "batchId": "14",
    "groupName": "（01）",
    "groupInfo": "首选历史，再选不限",
    "provinceControlScore": 474,
    "admissions": "2",
    "level": "本科",
    "nature": "公办",
    "city": "银川市",
    "f985": 2,
    "f211": 1,
    "dualClass": "双一流"
  },
  {
    "province": "宁夏",
    "year": 2023,
    "track": "历史类",
    "schoolName": "宁夏大学",
    "schoolId": 544,
    "minScore": 574,
    "minRank": 4876,
    "avgScore": "-",
    "batch": "本科批",
    "batchId": "14",
    "groupName": "(01)",
    "groupInfo": "首选历史，再选不限",
    "provinceControlScore": 426,
    "admissions": "2",
    "level": "本科",
    "nature": "公办",
    "city": "银川市",
    "f985": 2,
    "f211": 1,
    "dualClass": "双一流"
  },
  {
    "province": "宁夏",
    "year": 2023,
    "track": "历史类",
    "schoolName": "宁夏大学",
    "schoolId": 544,
    "minScore": 574,
    "minRank": 6113,
    "avgScore": "-",
    "batch": "本科批",
    "batchId": "14",
    "groupName": "",
    "groupInfo": "",
    "provinceControlScore": 430,
    "admissions": "2",
    "level": "本科",
    "nature": "公办",
    "city": "银川市",
    "f985": 2,
    "f211": 1,
    "dualClass": "双一流"
  },
  {
    "province": "宁夏",
    "year": 2023,
    "track": "历史类",
    "schoolName": "宁夏大学",
    "schoolId": 544,
    "minScore": 568,
    "minRank": 5766,
    "avgScore": "-",
    "batch": "本科批",
    "batchId": "14",
    "groupName": "(02)",
    "groupInfo": "首选历史，再选不限",
    "provinceControlScore": 426,
    "admissions": "2",
    "level": "本科",
    "nature": "公办",
    "city": "银川市",
    "f985": 2,
    "f211": 1,
    "dualClass": "双一流"
  },
  {
    "province": "宁夏",
    "year": 2023,
    "track": "历史类",
    "schoolName": "宁夏大学",
    "schoolId": 544,
    "minScore": 568,
    "minRank": 3965,
    "avgScore": "-",
    "batch": "本科批",
    "batchId": "14",
    "groupName": "2989（L509）",
    "groupInfo": "首选历史，再选化学/地理(2选1)",
    "provinceControlScore": 453,
    "admissions": "2",
    "level": "本科",
    "nature": "公办",
    "city": "银川市",
    "f985": 2,
    "f211": 1,
    "dualClass": "双一流"
  },
  {
    "province": "宁夏",
    "year": 2023,
    "track": "历史类",
    "schoolName": "宁夏大学",
    "schoolId": 544,
    "minScore": 565,
    "minRank": 7770,
    "avgScore": "-",
    "batch": "本科批",
    "batchId": "14",
    "groupName": "",
    "groupInfo": "",
    "provinceControlScore": 430,
    "admissions": "2",
    "level": "本科",
    "nature": "公办",
    "city": "银川市",
    "f985": 2,
    "f211": 1,
    "dualClass": "双一流"
  },
  {
    "province": "宁夏",
    "year": 2023,
    "track": "历史类",
    "schoolName": "宁夏大学",
    "schoolId": 544,
    "minScore": 565,
    "minRank": 10463,
    "avgScore": "-",
    "batch": "本科批",
    "batchId": "14",
    "groupName": "（201）",
    "groupInfo": "首选历史，再选不限",
    "provinceControlScore": 433,
    "admissions": "2",
    "level": "本科",
    "nature": "公办",
    "city": "银川市",
    "f985": 2,
    "f211": 1,
    "dualClass": "双一流"
  },
  {
    "province": "宁夏",
    "year": 2023,
    "track": "历史类",
    "schoolName": "宁夏大学",
    "schoolId": 544,
    "minScore": 557,
    "minRank": 6385,
    "avgScore": "-",
    "batch": "本科批",
    "batchId": "14",
    "groupName": "（103）",
    "groupInfo": "首选历史，再选化学/地理(2选1)",
    "provinceControlScore": 428,
    "admissions": "2",
    "level": "本科",
    "nature": "公办",
    "city": "银川市",
    "f985": 2,
    "f211": 1,
    "dualClass": "双一流"
  },
  {
    "province": "宁夏",
    "year": 2023,
    "track": "历史类",
    "schoolName": "宁夏大学",
    "schoolId": 544,
    "minScore": 556,
    "minRank": 6524,
    "avgScore": "-",
    "batch": "本科批",
    "batchId": "14",
    "groupName": "（104）",
    "groupInfo": "首选历史，再选思想政治",
    "provinceControlScore": 428,
    "admissions": "2",
    "level": "本科",
    "nature": "公办",
    "city": "银川市",
    "f985": 2,
    "f211": 1,
    "dualClass": "双一流"
  },
  {
    "province": "宁夏",
    "year": 2023,
    "track": "历史类",
    "schoolName": "宁夏大学",
    "schoolId": 544,
    "minScore": 556,
    "minRank": 6524,
    "avgScore": "-",
    "batch": "本科批",
    "batchId": "14",
    "groupName": "（101）",
    "groupInfo": "首选历史，再选不限",
    "provinceControlScore": 428,
    "admissions": "2",
    "level": "本科",
    "nature": "公办",
    "city": "银川市",
    "f985": 2,
    "f211": 1,
    "dualClass": "双一流"
  },
  {
    "province": "宁夏",
    "year": 2023,
    "track": "历史类",
    "schoolName": "宁夏大学",
    "schoolId": 544,
    "minScore": 554,
    "minRank": 5325,
    "avgScore": "-",
    "batch": "本科批",
    "batchId": "14",
    "groupName": "2989（L999）",
    "groupInfo": "首选历史，再选不限",
    "provinceControlScore": 453,
    "admissions": "2",
    "level": "本科",
    "nature": "公办",
    "city": "银川市",
    "f985": 2,
    "f211": 1,
    "dualClass": "双一流"
  },
  {
    "province": "宁夏",
    "year": 2023,
    "track": "历史类",
    "schoolName": "宁夏大学",
    "schoolId": 544,
    "minScore": 537,
    "minRank": 7411,
    "avgScore": "-",
    "batch": "本科批",
    "batchId": "14",
    "groupName": "2990（L999）",
    "groupInfo": "首选历史，再选不限",
    "provinceControlScore": 453,
    "admissions": "2",
    "level": "本科",
    "nature": "公办",
    "city": "银川市",
    "f985": 2,
    "f211": 1,
    "dualClass": "双一流"
  },
  {
    "province": "宁夏",
    "year": 2023,
    "track": "历史类",
    "schoolName": "宁夏大学",
    "schoolId": 544,
    "minScore": 531,
    "minRank": 7240,
    "avgScore": "-",
    "batch": "本科批",
    "batchId": "14",
    "groupName": "",
    "groupInfo": "",
    "provinceControlScore": 404,
    "admissions": "2",
    "level": "本科",
    "nature": "公办",
    "city": "银川市",
    "f985": 2,
    "f211": 1,
    "dualClass": "双一流"
  },
  {
    "province": "宁夏",
    "year": 2023,
    "track": "历史类",
    "schoolName": "宁夏大学",
    "schoolId": 544,
    "minScore": 529,
    "minRank": 6401,
    "avgScore": "-",
    "batch": "本科批",
    "batchId": "14",
    "groupName": "",
    "groupInfo": "",
    "provinceControlScore": 407,
    "admissions": "2",
    "level": "本科",
    "nature": "公办",
    "city": "银川市",
    "f985": 2,
    "f211": 1,
    "dualClass": "双一流"
  },
  {
    "province": "宁夏",
    "year": 2023,
    "track": "历史类",
    "schoolName": "宁夏大学",
    "schoolId": 544,
    "minScore": 521,
    "minRank": 13691,
    "avgScore": "-",
    "batch": "本科批",
    "batchId": "14",
    "groupName": "（202）",
    "groupInfo": "首选历史，再选不限",
    "provinceControlScore": 428,
    "admissions": "2",
    "level": "本科",
    "nature": "公办",
    "city": "银川市",
    "f985": 2,
    "f211": 1,
    "dualClass": "双一流"
  },
  {
    "province": "宁夏",
    "year": 2023,
    "track": "历史类",
    "schoolName": "北方民族大学",
    "schoolId": 545,
    "minScore": 518,
    "minRank": 31921,
    "avgScore": "-",
    "batch": "本科批",
    "batchId": "14",
    "groupName": "（01）",
    "groupInfo": "首选历史，再选不限",
    "provinceControlScore": 474,
    "admissions": "2",
    "level": "本科",
    "nature": "公办",
    "city": "银川市",
    "f985": 2,
    "f211": 2,
    "dualClass": ""
  },
  {
    "province": "宁夏",
    "year": 2023,
    "track": "历史类",
    "schoolName": "北方民族大学",
    "schoolId": 545,
    "minScore": 516,
    "minRank": 30127,
    "avgScore": "-",
    "batch": "本科批",
    "batchId": "14",
    "groupName": "（202）",
    "groupInfo": "首选历史，再选思想政治/地理(2选1)",
    "provinceControlScore": 433,
    "admissions": "2",
    "level": "本科",
    "nature": "公办",
    "city": "银川市",
    "f985": 2,
    "f211": 2,
    "dualClass": ""
  },
  {
    "province": "宁夏",
    "year": 2023,
    "track": "历史类",
    "schoolName": "北方民族大学",
    "schoolId": 545,
    "minScore": 510,
    "minRank": 33665,
    "avgScore": "-",
    "batch": "本科批",
    "batchId": "14",
    "groupName": "（201）",
    "groupInfo": "首选历史，再选不限",
    "provinceControlScore": 433,
    "admissions": "2",
    "level": "本科",
    "nature": "公办",
    "city": "银川市",
    "f985": 2,
    "f211": 2,
    "dualClass": ""
  },
  {
    "province": "宁夏",
    "year": 2023,
    "track": "历史类",
    "schoolName": "北方民族大学",
    "schoolId": 545,
    "minScore": 509,
    "minRank": 24758,
    "avgScore": "-",
    "batch": "本科批",
    "batchId": "14",
    "groupName": "",
    "groupInfo": "",
    "provinceControlScore": 430,
    "admissions": "2",
    "level": "本科",
    "nature": "公办",
    "city": "银川市",
    "f985": 2,
    "f211": 2,
    "dualClass": ""
  },
  {
    "province": "宁夏",
    "year": 2023,
    "track": "历史类",
    "schoolName": "北方民族大学",
    "schoolId": 545,
    "minScore": 508,
    "minRank": 36849,
    "avgScore": "-",
    "batch": "本科批",
    "batchId": "14",
    "groupName": "（02）",
    "groupInfo": "首选历史，再选思想政治/地理(2选1)",
    "provinceControlScore": 474,
    "admissions": "2",
    "level": "本科",
    "nature": "公办",
    "city": "银川市",
    "f985": 2,
    "f211": 2,
    "dualClass": ""
  },
  {
    "province": "宁夏",
    "year": 2023,
    "track": "历史类",
    "schoolName": "北方民族大学",
    "schoolId": 545,
    "minScore": 506,
    "minRank": 19149,
    "avgScore": "-",
    "batch": "本科批",
    "batchId": "14",
    "groupName": "(05)",
    "groupInfo": "首选历史，再选思想政治",
    "provinceControlScore": 426,
    "admissions": "2",
    "level": "本科",
    "nature": "公办",
    "city": "银川市",
    "f985": 2,
    "f211": 2,
    "dualClass": ""
  },
  {
    "province": "宁夏",
    "year": 2023,
    "track": "历史类",
    "schoolName": "北方民族大学",
    "schoolId": 545,
    "minScore": 505,
    "minRank": 12406,
    "avgScore": "-",
    "batch": "本科批",
    "batchId": "14",
    "groupName": "2287（L709）",
    "groupInfo": "首选历史，再选思想政治/地理(2选1)",
    "provinceControlScore": 453,
    "admissions": "2",
    "level": "本科",
    "nature": "公办",
    "city": "银川市",
    "f985": 2,
    "f211": 2,
    "dualClass": ""
  },
  {
    "province": "宁夏",
    "year": 2023,
    "track": "历史类",
    "schoolName": "北方民族大学",
    "schoolId": 545,
    "minScore": 502,
    "minRank": 20284,
    "avgScore": "-",
    "batch": "本科批",
    "batchId": "14",
    "groupName": "(08)",
    "groupInfo": "首选历史，再选思想政治/地理(2选1)",
    "provinceControlScore": 426,
    "admissions": "2",
    "level": "本科",
    "nature": "公办",
    "city": "银川市",
    "f985": 2,
    "f211": 2,
    "dualClass": ""
  },
  {
    "province": "宁夏",
    "year": 2023,
    "track": "历史类",
    "schoolName": "北方民族大学",
    "schoolId": 545,
    "minScore": 498,
    "minRank": 21434,
    "avgScore": "-",
    "batch": "本科批",
    "batchId": "14",
    "groupName": "(07)",
    "groupInfo": "首选历史，再选思想政治",
    "provinceControlScore": 426,
    "admissions": "2",
    "level": "本科",
    "nature": "公办",
    "city": "银川市",
    "f985": 2,
    "f211": 2,
    "dualClass": ""
  },
  {
    "province": "宁夏",
    "year": 2023,
    "track": "历史类",
    "schoolName": "北方民族大学",
    "schoolId": 545,
    "minScore": 498,
    "minRank": 21434,
    "avgScore": "-",
    "batch": "本科批",
    "batchId": "14",
    "groupName": "(06)",
    "groupInfo": "首选历史，再选思想政治",
    "provinceControlScore": 426,
    "admissions": "2",
    "level": "本科",
    "nature": "公办",
    "city": "银川市",
    "f985": 2,
    "f211": 2,
    "dualClass": ""
  },
  {
    "province": "宁夏",
    "year": 2023,
    "track": "历史类",
    "schoolName": "北方民族大学",
    "schoolId": 545,
    "minScore": 496,
    "minRank": 22031,
    "avgScore": "-",
    "batch": "本科批",
    "batchId": "14",
    "groupName": "(02)",
    "groupInfo": "首选历史，再选不限",
    "provinceControlScore": 426,
    "admissions": "2",
    "level": "本科",
    "nature": "公办",
    "city": "银川市",
    "f985": 2,
    "f211": 2,
    "dualClass": ""
  },
  {
    "province": "宁夏",
    "year": 2023,
    "track": "历史类",
    "schoolName": "北方民族大学",
    "schoolId": 545,
    "minScore": 496,
    "minRank": 22031,
    "avgScore": "-",
    "batch": "本科批",
    "batchId": "14",
    "groupName": "(01)",
    "groupInfo": "首选历史，再选不限",
    "provinceControlScore": 426,
    "admissions": "2",
    "level": "本科",
    "nature": "公办",
    "city": "银川市",
    "f985": 2,
    "f211": 2,
    "dualClass": ""
  },
  {
    "province": "宁夏",
    "year": 2023,
    "track": "历史类",
    "schoolName": "北方民族大学",
    "schoolId": 545,
    "minScore": 495,
    "minRank": 22041,
    "avgScore": "-",
    "batch": "本科批",
    "batchId": "14",
    "groupName": "（108）",
    "groupInfo": "首选历史，再选思想政治",
    "provinceControlScore": 428,
    "admissions": "2",
    "level": "本科",
    "nature": "公办",
    "city": "银川市",
    "f985": 2,
    "f211": 2,
    "dualClass": ""
  },
  {
    "province": "宁夏",
    "year": 2023,
    "track": "历史类",
    "schoolName": "北方民族大学",
    "schoolId": 545,
    "minScore": 494,
    "minRank": 22653,
    "avgScore": "-",
    "batch": "本科批",
    "batchId": "14",
    "groupName": "(04)",
    "groupInfo": "首选历史，再选思想政治",
    "provinceControlScore": 426,
    "admissions": "2",
    "level": "本科",
    "nature": "公办",
    "city": "银川市",
    "f985": 2,
    "f211": 2,
    "dualClass": ""
  },
  {
    "province": "宁夏",
    "year": 2023,
    "track": "历史类",
    "schoolName": "北方民族大学",
    "schoolId": 545,
    "minScore": 494,
    "minRank": 14522,
    "avgScore": "-",
    "batch": "本科批",
    "batchId": "14",
    "groupName": "2287（L999）",
    "groupInfo": "首选历史，再选不限",
    "provinceControlScore": 453,
    "admissions": "2",
    "level": "本科",
    "nature": "公办",
    "city": "银川市",
    "f985": 2,
    "f211": 2,
    "dualClass": ""
  },
  {
    "province": "宁夏",
    "year": 2023,
    "track": "历史类",
    "schoolName": "北方民族大学",
    "schoolId": 545,
    "minScore": 487,
    "minRank": 24890,
    "avgScore": "-",
    "batch": "本科批",
    "batchId": "14",
    "groupName": "(03)",
    "groupInfo": "首选历史，再选不限",
    "provinceControlScore": 426,
    "admissions": "2",
    "level": "本科",
    "nature": "公办",
    "city": "银川市",
    "f985": 2,
    "f211": 2,
    "dualClass": ""
  },
  {
    "province": "宁夏",
    "year": 2023,
    "track": "历史类",
    "schoolName": "北方民族大学",
    "schoolId": 545,
    "minScore": 487,
    "minRank": 25253,
    "avgScore": "-",
    "batch": "本科批",
    "batchId": "14",
    "groupName": "（109）",
    "groupInfo": "首选历史，再选思想政治",
    "provinceControlScore": 428,
    "admissions": "2",
    "level": "本科",
    "nature": "公办",
    "city": "银川市",
    "f985": 2,
    "f211": 2,
    "dualClass": ""
  },
  {
    "province": "宁夏",
    "year": 2023,
    "track": "历史类",
    "schoolName": "北方民族大学",
    "schoolId": 545,
    "minScore": 477,
    "minRank": 15431,
    "avgScore": "-",
    "batch": "本科批",
    "batchId": "14",
    "groupName": "",
    "groupInfo": "",
    "provinceControlScore": 404,
    "admissions": "2",
    "level": "本科",
    "nature": "公办",
    "city": "银川市",
    "f985": 2,
    "f211": 2,
    "dualClass": ""
  },
  {
    "province": "宁夏",
    "year": 2023,
    "track": "历史类",
    "schoolName": "宁夏大学新华学院",
    "schoolId": 2576,
    "minScore": 477,
    "minRank": 52277,
    "avgScore": "-",
    "batch": "本科批",
    "batchId": "14",
    "groupName": "（01）",
    "groupInfo": "首选历史，再选不限",
    "provinceControlScore": 474,
    "admissions": "2",
    "level": "本科",
    "nature": "民办",
    "city": "银川市",
    "f985": 2,
    "f211": 2,
    "dualClass": ""
  },
  {
    "province": "宁夏",
    "year": 2023,
    "track": "历史类",
    "schoolName": "北方民族大学",
    "schoolId": 545,
    "minScore": 476,
    "minRank": 16045,
    "avgScore": "-",
    "batch": "本科批",
    "batchId": "14",
    "groupName": "",
    "groupInfo": "",
    "provinceControlScore": 407,
    "admissions": "2",
    "level": "本科",
    "nature": "公办",
    "city": "银川市",
    "f985": 2,
    "f211": 2,
    "dualClass": ""
  },
  {
    "province": "宁夏",
    "year": 2023,
    "track": "历史类",
    "schoolName": "北方民族大学",
    "schoolId": 545,
    "minScore": 474,
    "minRank": 31088,
    "avgScore": "-",
    "batch": "本科批",
    "batchId": "14",
    "groupName": "（110）",
    "groupInfo": "首选历史，再选思想政治/地理(2选1)",
    "provinceControlScore": 428,
    "admissions": "2",
    "level": "本科",
    "nature": "公办",
    "city": "银川市",
    "f985": 2,
    "f211": 2,
    "dualClass": ""
  },
  {
    "province": "宁夏",
    "year": 2023,
    "track": "历史类",
    "schoolName": "北方民族大学",
    "schoolId": 545,
    "minScore": 474,
    "minRank": 31088,
    "avgScore": "-",
    "batch": "本科批",
    "batchId": "14",
    "groupName": "（106）",
    "groupInfo": "首选历史，再选不限",
    "provinceControlScore": 428,
    "admissions": "2",
    "level": "本科",
    "nature": "公办",
    "city": "银川市",
    "f985": 2,
    "f211": 2,
    "dualClass": ""
  },
  {
    "province": "宁夏",
    "year": 2023,
    "track": "历史类",
    "schoolName": "宁夏理工学院",
    "schoolId": 2288,
    "minScore": 474,
    "minRank": 58724,
    "avgScore": 477,
    "batch": "本科批",
    "batchId": "14",
    "groupName": "（202）",
    "groupInfo": "首选历史，再选不限",
    "provinceControlScore": "-",
    "admissions": "2",
    "level": "本科",
    "nature": "民办",
    "city": "石嘴山市",
    "f985": 2,
    "f211": 2,
    "dualClass": ""
  },
  {
    "province": "宁夏",
    "year": 2023,
    "track": "历史类",
    "schoolName": "宁夏理工学院",
    "schoolId": 2288,
    "minScore": 474,
    "minRank": 53767,
    "avgScore": 476,
    "batch": "本科批",
    "batchId": "14",
    "groupName": "（01）",
    "groupInfo": "首选历史，再选不限",
    "provinceControlScore": "-",
    "admissions": "2",
    "level": "本科",
    "nature": "民办",
    "city": "石嘴山市",
    "f985": 2,
    "f211": 2,
    "dualClass": ""
  },
  {
    "province": "宁夏",
    "year": 2023,
    "track": "历史类",
    "schoolName": "北方民族大学",
    "schoolId": 545,
    "minScore": 473,
    "minRank": 31604,
    "avgScore": "-",
    "batch": "本科批",
    "batchId": "14",
    "groupName": "（105）",
    "groupInfo": "首选历史，再选不限",
    "provinceControlScore": 428,
    "admissions": "2",
    "level": "本科",
    "nature": "公办",
    "city": "银川市",
    "f985": 2,
    "f211": 2,
    "dualClass": ""
  },
  {
    "province": "宁夏",
    "year": 2023,
    "track": "历史类",
    "schoolName": "宁夏大学新华学院",
    "schoolId": 2576,
    "minScore": 473,
    "minRank": 29629,
    "avgScore": "-",
    "batch": "本科批",
    "batchId": "14",
    "groupName": "(01)",
    "groupInfo": "首选历史，再选不限",
    "provinceControlScore": 426,
    "admissions": "2",
    "level": "本科",
    "nature": "民办",
    "city": "银川市",
    "f985": 2,
    "f211": 2,
    "dualClass": ""
  },
  {
    "province": "宁夏",
    "year": 2023,
    "track": "历史类",
    "schoolName": "北方民族大学",
    "schoolId": 545,
    "minScore": 472,
    "minRank": 17010,
    "avgScore": "-",
    "batch": "本科批",
    "batchId": "14",
    "groupName": "",
    "groupInfo": "",
    "provinceControlScore": 407,
    "admissions": "2",
    "level": "本科",
    "nature": "公办",
    "city": "银川市",
    "f985": 2,
    "f211": 2,
    "dualClass": ""
  },
  {
    "province": "宁夏",
    "year": 2023,
    "track": "历史类",
    "schoolName": "宁夏大学新华学院",
    "schoolId": 2576,
    "minScore": 472,
    "minRank": 19320,
    "avgScore": "-",
    "batch": "本科批",
    "batchId": "14",
    "groupName": "2992（L999）",
    "groupInfo": "首选历史，再选不限",
    "provinceControlScore": 453,
    "admissions": "2",
    "level": "本科",
    "nature": "民办",
    "city": "银川市",
    "f985": 2,
    "f211": 2,
    "dualClass": ""
  },
  {
    "province": "宁夏",
    "year": 2023,
    "track": "历史类",
    "schoolName": "北方民族大学",
    "schoolId": 545,
    "minScore": 471,
    "minRank": 32562,
    "avgScore": "-",
    "batch": "本科批",
    "batchId": "14",
    "groupName": "（111）",
    "groupInfo": "首选历史，再选思想政治/地理(2选1)",
    "provinceControlScore": 428,
    "admissions": "2",
    "level": "本科",
    "nature": "公办",
    "city": "银川市",
    "f985": 2,
    "f211": 2,
    "dualClass": ""
  },
  {
    "province": "宁夏",
    "year": 2023,
    "track": "历史类",
    "schoolName": "北方民族大学",
    "schoolId": 545,
    "minScore": 470,
    "minRank": 17521,
    "avgScore": "-",
    "batch": "本科批",
    "batchId": "14",
    "groupName": "",
    "groupInfo": "",
    "provinceControlScore": 407,
    "admissions": "2",
    "level": "本科",
    "nature": "公办",
    "city": "银川市",
    "f985": 2,
    "f211": 2,
    "dualClass": ""
  },
  {
    "province": "宁夏",
    "year": 2023,
    "track": "历史类",
    "schoolName": "北方民族大学",
    "schoolId": 545,
    "minScore": 468,
    "minRank": 17044,
    "avgScore": "-",
    "batch": "本科批",
    "batchId": "14",
    "groupName": "",
    "groupInfo": "",
    "provinceControlScore": 404,
    "admissions": "2",
    "level": "本科",
    "nature": "公办",
    "city": "银川市",
    "f985": 2,
    "f211": 2,
    "dualClass": ""
  },
  {
    "province": "宁夏",
    "year": 2023,
    "track": "历史类",
    "schoolName": "北方民族大学",
    "schoolId": 545,
    "minScore": 467,
    "minRank": 34672,
    "avgScore": "-",
    "batch": "本科批",
    "batchId": "14",
    "groupName": "（107）",
    "groupInfo": "首选历史，再选思想政治",
    "provinceControlScore": 428,
    "admissions": "2",
    "level": "本科",
    "nature": "公办",
    "city": "银川市",
    "f985": 2,
    "f211": 2,
    "dualClass": ""
  },
  {
    "province": "宁夏",
    "year": 2023,
    "track": "历史类",
    "schoolName": "宁夏师范大学",
    "schoolId": 1241,
    "minScore": 462,
    "minRank": 49202,
    "avgScore": "-",
    "batch": "本科批",
    "batchId": "14",
    "groupName": "",
    "groupInfo": "",
    "provinceControlScore": 430,
    "admissions": "2",
    "level": "本科",
    "nature": "公办",
    "city": "固原市",
    "f985": 2,
    "f211": 2,
    "dualClass": ""
  },
  {
    "province": "宁夏",
    "year": 2023,
    "track": "历史类",
    "schoolName": "宁夏大学新华学院",
    "schoolId": 2576,
    "minScore": 462,
    "minRank": 19471,
    "avgScore": "-",
    "batch": "本科批",
    "batchId": "14",
    "groupName": "",
    "groupInfo": "",
    "provinceControlScore": 407,
    "admissions": "2",
    "level": "本科",
    "nature": "民办",
    "city": "银川市",
    "f985": 2,
    "f211": 2,
    "dualClass": ""
  },
  {
    "province": "宁夏",
    "year": 2023,
    "track": "历史类",
    "schoolName": "宁夏师范大学",
    "schoolId": 1241,
    "minScore": 460,
    "minRank": 38497,
    "avgScore": "-",
    "batch": "本科批",
    "batchId": "14",
    "groupName": "（101）",
    "groupInfo": "首选历史，再选不限",
    "provinceControlScore": 428,
    "admissions": "2",
    "level": "本科",
    "nature": "公办",
    "city": "固原市",
    "f985": 2,
    "f211": 2,
    "dualClass": ""
  },
  {
    "province": "宁夏",
    "year": 2023,
    "track": "历史类",
    "schoolName": "宁夏理工学院",
    "schoolId": 2288,
    "minScore": 449,
    "minRank": 38712,
    "avgScore": 453,
    "batch": "本科批",
    "batchId": "14",
    "groupName": "(01)",
    "groupInfo": "首选历史，再选不限",
    "provinceControlScore": "-",
    "admissions": "2",
    "level": "本科",
    "nature": "民办",
    "city": "石嘴山市",
    "f985": 2,
    "f211": 2,
    "dualClass": ""
  },
  {
    "province": "宁夏",
    "year": 2023,
    "track": "历史类",
    "schoolName": "宁夏大学新华学院",
    "schoolId": 2576,
    "minScore": 448,
    "minRank": 58117,
    "avgScore": "-",
    "batch": "本科批",
    "batchId": "14",
    "groupName": "",
    "groupInfo": "",
    "provinceControlScore": 430,
    "admissions": "2",
    "level": "本科",
    "nature": "民办",
    "city": "银川市",
    "f985": 2,
    "f211": 2,
    "dualClass": ""
  },
  {
    "province": "宁夏",
    "year": 2023,
    "track": "历史类",
    "schoolName": "宁夏理工学院",
    "schoolId": 2288,
    "minScore": 446,
    "minRank": 25757,
    "avgScore": 452,
    "batch": "本科批",
    "batchId": "14",
    "groupName": "2993（L999）",
    "groupInfo": "首选历史，再选不限",
    "provinceControlScore": "-",
    "admissions": "2",
    "level": "本科",
    "nature": "民办",
    "city": "石嘴山市",
    "f985": 2,
    "f211": 2,
    "dualClass": ""
  },
  {
    "province": "宁夏",
    "year": 2023,
    "track": "历史类",
    "schoolName": "宁夏理工学院",
    "schoolId": 2288,
    "minScore": 440,
    "minRank": 49902,
    "avgScore": 443,
    "batch": "本科批",
    "batchId": "14",
    "groupName": "（101）",
    "groupInfo": "首选历史，再选不限",
    "provinceControlScore": "-",
    "admissions": "2",
    "level": "本科",
    "nature": "民办",
    "city": "石嘴山市",
    "f985": 2,
    "f211": 2,
    "dualClass": ""
  },
  {
    "province": "宁夏",
    "year": 2023,
    "track": "历史类",
    "schoolName": "银川科技学院",
    "schoolId": 2615,
    "minScore": 439,
    "minRank": 64168,
    "avgScore": "-",
    "batch": "本科批",
    "batchId": "14",
    "groupName": "",
    "groupInfo": "",
    "provinceControlScore": 430,
    "admissions": "2",
    "level": "本科",
    "nature": "民办",
    "city": "银川市",
    "f985": 2,
    "f211": 2,
    "dualClass": ""
  },
  {
    "province": "宁夏",
    "year": 2023,
    "track": "历史类",
    "schoolName": "银川科技学院",
    "schoolId": 2615,
    "minScore": 437,
    "minRank": 51731,
    "avgScore": "-",
    "batch": "本科批",
    "batchId": "14",
    "groupName": "（101）",
    "groupInfo": "首选历史，再选不限",
    "provinceControlScore": 428,
    "admissions": "2",
    "level": "本科",
    "nature": "民办",
    "city": "银川市",
    "f985": 2,
    "f211": 2,
    "dualClass": ""
  },
  {
    "province": "宁夏",
    "year": 2023,
    "track": "历史类",
    "schoolName": "银川科技学院",
    "schoolId": 2615,
    "minScore": 434,
    "minRank": 45056,
    "avgScore": "-",
    "batch": "本科批",
    "batchId": "14",
    "groupName": "(01)",
    "groupInfo": "首选历史，再选不限",
    "provinceControlScore": 426,
    "admissions": "2",
    "level": "本科",
    "nature": "民办",
    "city": "银川市",
    "f985": 2,
    "f211": 2,
    "dualClass": ""
  },
  {
    "province": "宁夏",
    "year": 2023,
    "track": "历史类",
    "schoolName": "宁夏理工学院",
    "schoolId": 2288,
    "minScore": 434,
    "minRank": 67682,
    "avgScore": 447,
    "batch": "本科批",
    "batchId": "14",
    "groupName": "",
    "groupInfo": "",
    "provinceControlScore": "-",
    "admissions": "2",
    "level": "本科",
    "nature": "民办",
    "city": "石嘴山市",
    "f985": 2,
    "f211": 2,
    "dualClass": ""
  },
  {
    "province": "宁夏",
    "year": 2023,
    "track": "历史类",
    "schoolName": "银川能源学院",
    "schoolId": 2289,
    "minScore": 434,
    "minRank": 67682,
    "avgScore": "-",
    "batch": "本科批",
    "batchId": "14",
    "groupName": "",
    "groupInfo": "",
    "provinceControlScore": 430,
    "admissions": "2",
    "level": "本科",
    "nature": "民办",
    "city": "银川市",
    "f985": 2,
    "f211": 2,
    "dualClass": ""
  },
  {
    "province": "宁夏",
    "year": 2023,
    "track": "历史类",
    "schoolName": "银川能源学院",
    "schoolId": 2289,
    "minScore": 430,
    "minRank": 70593,
    "avgScore": "-",
    "batch": "本科批",
    "batchId": "14",
    "groupName": "",
    "groupInfo": "",
    "provinceControlScore": 430,
    "admissions": "2",
    "level": "本科",
    "nature": "民办",
    "city": "银川市",
    "f985": 2,
    "f211": 2,
    "dualClass": ""
  },
  {
    "province": "宁夏",
    "year": 2023,
    "track": "历史类",
    "schoolName": "宁夏理工学院",
    "schoolId": 2288,
    "minScore": 427,
    "minRank": 28892,
    "avgScore": "-",
    "batch": "本科批",
    "batchId": "14",
    "groupName": "",
    "groupInfo": "",
    "provinceControlScore": 407,
    "admissions": "2",
    "level": "本科",
    "nature": "民办",
    "city": "石嘴山市",
    "f985": 2,
    "f211": 2,
    "dualClass": ""
  },
  {
    "province": "宁夏",
    "year": 2023,
    "track": "历史类",
    "schoolName": "宁夏理工学院",
    "schoolId": 2288,
    "minScore": 411,
    "minRank": 28400,
    "avgScore": 443,
    "batch": "本科批",
    "batchId": "14",
    "groupName": "",
    "groupInfo": "",
    "provinceControlScore": "-",
    "admissions": "2",
    "level": "本科",
    "nature": "民办",
    "city": "石嘴山市",
    "f985": 2,
    "f211": 2,
    "dualClass": ""
  },
  {
    "province": "宁夏",
    "year": 2023,
    "track": "历史类",
    "schoolName": "宁夏职业技术大学",
    "schoolId": 2283,
    "minScore": 318,
    "minRank": 60234,
    "avgScore": "-",
    "batch": "专科提前批",
    "batchId": "11",
    "groupName": "",
    "groupInfo": "",
    "provinceControlScore": 180,
    "admissions": "2",
    "level": "本科",
    "nature": "公办",
    "city": "银川市",
    "f985": 2,
    "f211": 2,
    "dualClass": ""
  },
  {
    "province": "宁夏",
    "year": 2023,
    "track": "历史类",
    "schoolName": "宁夏警官职业学院",
    "schoolId": 2286,
    "minScore": 374,
    "minRank": 115466,
    "avgScore": "-",
    "batch": "专科批",
    "batchId": "10",
    "groupName": "",
    "groupInfo": "",
    "provinceControlScore": 200,
    "admissions": "2",
    "level": "专科（高职）",
    "nature": "公办",
    "city": "银川市",
    "f985": 2,
    "f211": 2,
    "dualClass": ""
  },
  {
    "province": "宁夏",
    "year": 2023,
    "track": "历史类",
    "schoolName": "宁夏幼儿师范高等专科学校",
    "schoolId": 3409,
    "minScore": 358,
    "minRank": 130006,
    "avgScore": "-",
    "batch": "专科批",
    "batchId": "10",
    "groupName": "",
    "groupInfo": "",
    "provinceControlScore": 200,
    "admissions": "2",
    "level": "专科（高职）",
    "nature": "公办",
    "city": "银川市",
    "f985": 2,
    "f211": 2,
    "dualClass": ""
  },
  {
    "province": "宁夏",
    "year": 2023,
    "track": "历史类",
    "schoolName": "石嘴山工贸职业技术学院",
    "schoolId": 3535,
    "minScore": 295,
    "minRank": 184350,
    "avgScore": "-",
    "batch": "专科批",
    "batchId": "10",
    "groupName": "",
    "groupInfo": "",
    "provinceControlScore": 200,
    "admissions": "2",
    "level": "专科（高职）",
    "nature": "公办",
    "city": "石嘴山市",
    "f985": 2,
    "f211": 2,
    "dualClass": ""
  },
  {
    "province": "宁夏",
    "year": 2023,
    "track": "历史类",
    "schoolName": "宁夏艺术职业学院",
    "schoolId": 3410,
    "minScore": 280,
    "minRank": 193420,
    "avgScore": "-",
    "batch": "专科批",
    "batchId": "10",
    "groupName": "",
    "groupInfo": "",
    "provinceControlScore": 200,
    "admissions": "2",
    "level": "专科（高职）",
    "nature": "公办",
    "city": "银川市",
    "f985": 2,
    "f211": 2,
    "dualClass": ""
  },
  {
    "province": "宁夏",
    "year": 2023,
    "track": "历史类",
    "schoolName": "银川科技学院",
    "schoolId": 2615,
    "minScore": 232,
    "minRank": 218110,
    "avgScore": "-",
    "batch": "专科批",
    "batchId": "10",
    "groupName": "",
    "groupInfo": "",
    "provinceControlScore": 200,
    "admissions": "2",
    "level": "本科",
    "nature": "民办",
    "city": "银川市",
    "f985": 2,
    "f211": 2,
    "dualClass": ""
  },
  {
    "province": "宁夏",
    "year": 2023,
    "track": "历史类",
    "schoolName": "银川科技学院",
    "schoolId": 2615,
    "minScore": 221,
    "minRank": 155459,
    "avgScore": "-",
    "batch": "专科批",
    "batchId": "10",
    "groupName": "（104）",
    "groupInfo": "首选历史，再选不限",
    "provinceControlScore": 200,
    "admissions": "2",
    "level": "本科",
    "nature": "民办",
    "city": "银川市",
    "f985": 2,
    "f211": 2,
    "dualClass": ""
  }
]